hipdf/__init__.py
hipdf/__version__.py
hipdf/core.py
hipdf/main.py
hipdf-0.2.0.dist-info/LICENSE
hipdf-0.2.0.dist-info/METADATA
hipdf-0.2.0.dist-info/WHEEL
hipdf-0.2.0.dist-info/entry_points.txt
hipdf-0.2.0.dist-info/top_level.txt
hipdf-0.2.0.dist-info/RECORD
