Metadata-Version: 2.1
Name: hipdf
Version: 0.2.0
Summary: Highlight the first word of English sentences in PDF file.
Home-page: https://github.com/CarlHey/hipdf
Author: heyy
Author-email: hey.ing@qq.com
License: MIT
Platform: UNKNOWN
Classifier: License :: OSI Approved :: MIT License
Classifier: Programming Language :: Python
Classifier: Programming Language :: Python :: 3
Classifier: Programming Language :: Python :: 3.6
Classifier: Programming Language :: Python :: Implementation :: CPython
Classifier: Programming Language :: Python :: Implementation :: PyPy
Requires-Python: >=3.6.0
Requires-Dist: PyMuPDF (>=1.18.4)
